funpoetry/__init__.py
funpoetry/command.py
funpoetry/version/__init__.py
funpoetry/version/upgrade.py
funpoetry-1.0.6.dist-info/LICENSE
funpoetry-1.0.6.dist-info/METADATA
funpoetry-1.0.6.dist-info/WHEEL
funpoetry-1.0.6.dist-info/entry_points.txt
funpoetry-1.0.6.dist-info/RECORD
