Metadata-Version: 2.1
Name: funpoetry
Version: 1.0.6
Summary: 
Author: farfun
Author-email: 1007530194@qq.com
Requires-Python: >=3.8,<4.0
Classifier: Programming Language :: Python :: 3
Classifier: Programming Language :: Python :: 3.8
Classifier: Programming Language :: Python :: 3.9
Classifier: Programming Language :: Python :: 3.10
Classifier: Programming Language :: Python :: 3.11
Classifier: Programming Language :: Python :: 3.12
Requires-Dist: poetry (>=1.8.3,<2.0.0)
Requires-Dist: toml (>=0.10.2,<0.11.0)
